<annotation>
	<folder>door_closed</folder>
	<filename>vid_frame (585).jpg</filename>
	<path>D:\wowexp\door\door_closed\vid_frame (585).jpg</path>
	<source>
		<database>Unknown</database>
	</source>
	<size>
		<width>320</width>
		<height>240</height>
		<depth>3</depth>
	</size>
	<segmented>0</segmented>
	<object>
		<name>closed</name>
		<pose>Unspecified</pose>
		<truncated>0</truncated>
		<difficult>0</difficult>
		<bndbox>
			<xmin>98</xmin>
			<ymin>2</ymin>
			<xmax>266</xmax>
			<ymax>108</ymax>
		</bndbox>
	</object>
</annotation>
